jimgw/__init__.py
jimgw/base.py
jimgw/constants.py
jimgw/jim.py
jimgw/prior.py
jimgw/transforms.py
jimgw/utils.py
jimgw/single_event/__init__.py
jimgw/single_event/detector.py
jimgw/single_event/likelihood.py
jimgw/single_event/prior.py
jimgw/single_event/runManager.py
jimgw/single_event/transforms.py
jimgw/single_event/utils.py
jimgw/single_event/wave.py
jimgw/single_event/waveform.py
jimgw-0.2.0.dist-info/METADATA
jimgw-0.2.0.dist-info/WHEEL
jimgw-0.2.0.dist-info/licenses/LICENSE
jimgw-0.2.0.dist-info/RECORD
