Metadata-Version: 2.3
Name: jimgw
Version: 0.2.0
Summary: Gravitatioanl wave data analysis tool in Jax
Author-email: "Kaze W. K. Wong" <kazewong.physics@gmail.com>
License: MIT License
License-File: LICENSE
Requires-Python: <=3.11,>=3.10
Requires-Dist: astropy>=6.1.4
Requires-Dist: beartype>=0.19.0
Requires-Dist: corner>=2.2.2
Requires-Dist: flowmc>=0.3.4
Requires-Dist: gwpy>=3.0.10
Requires-Dist: jax<=0.4.31,>=0.4.24
Requires-Dist: jaxtyping>=0.2.34
Requires-Dist: pytest>=8.3.3
Requires-Dist: ripplegw>=0.0.9
Requires-Dist: typed-argument-parser>=1.10.1
Provides-Extra: docs
Requires-Dist: mkdocs; extra == 'docs'
Requires-Dist: mkdocs-gen-files; extra == 'docs'
Requires-Dist: mkdocs-jupyter; extra == 'docs'
Requires-Dist: mkdocs-literate-nav; extra == 'docs'
Requires-Dist: mkdocs-material; extra == 'docs'
Requires-Dist: mkdocstrings[python]; extra == 'docs'
Requires-Dist: pymdown-extensions; extra == 'docs'
